{
  "job_id": "in-cc28ae7020596d65",
  "text": "You will likely hold an MSc or a BSc with relevant experience in a relevant discipline and have hands -on experience conducting human research studies under supervision. Essential MSc or BSc in Psychology, Human Factors, Cognitive Science, Cognitive Neuroscience or a closely related field Strong analytical, communication, and scientific writing skills Experience with human data collection and ethical research practices Familiarity with programming language (Python preferred) and data analysis tools (e.g.",
  "skills": [
    {
      "skill": "conduct human research studies",
      "type": "Hard",
      "bloom": "Apply",
      "confidence_score": 0.642,
      "confidence_tier": "Medium",
      "source": "BERT+GPT",
      "semantic_density": 0.82,
      "context_agreement": 0.9
    },
    {
      "skill": "analyze data",
      "type": "Hard",
      "bloom": "Analyze",
      "confidence_score": 0.647,
      "confidence_tier": "Medium",
      "source": "GPT",
      "semantic_density": 0.77,
      "context_agreement": 0.9
    },
    {
      "skill": "communicate ideas",
      "type": "Soft",
      "bloom": "N/A",
      "confidence_score": 0.603,
      "confidence_tier": "Medium",
      "source": "GPT",
      "semantic_density": 0.84,
      "context_agreement": 0.9
    },
    {
      "skill": "write scientific content",
      "type": "Hard",
      "bloom": "Create",
      "confidence_score": 0.654,
      "confidence_tier": "Medium",
      "source": "GPT",
      "semantic_density": 0.82,
      "context_agreement": 0.9
    },
    {
      "skill": "collect human data",
      "type": "Hard",
      "bloom": "Apply",
      "confidence_score": 0.622,
      "confidence_tier": "Medium",
      "source": "GPT",
      "semantic_density": 0.76,
      "context_agreement": 0.9
    },
    {
      "skill": "practice ethical research",
      "type": "Hard",
      "bloom": "Apply",
      "confidence_score": 0.656,
      "confidence_tier": "Medium",
      "source": "GPT",
      "semantic_density": 0.83,
      "context_agreement": 0.9
    },
    {
      "skill": "analytical",
      "type": "Hard",
      "bloom": "Apply",
      "confidence_score": 0.47,
      "confidence_tier": "Low",
      "source": "BERT (standalone)",
      "semantic_density": 0.9,
      "context_agreement": 0.81
    },
    {
      "skill": "communication",
      "type": "Soft",
      "bloom": "N/A",
      "confidence_score": 0.681,
      "confidence_tier": "Medium",
      "source": "BERT (standalone)",
      "semantic_density": 0.9,
      "context_agreement": 0.81
    }
  ],
  "knowledge": [
    {
      "knowledge": "Psychology",
      "confidence_score": 0.824,
      "confidence_tier": "High",
      "source": "BERT+GPT"
    },
    {
      "knowledge": "Human Factors",
      "confidence_score": 0.828,
      "confidence_tier": "High",
      "source": "BERT+GPT"
    },
    {
      "knowledge": "Cognitive Science",
      "confidence_score": 0.824,
      "confidence_tier": "High",
      "source": "BERT+GPT"
    },
    {
      "knowledge": "Cognitive Neuroscience",
      "confidence_score": 0.831,
      "confidence_tier": "High",
      "source": "BERT+GPT"
    },
    {
      "knowledge": "human data collection",
      "confidence_score": 0.831,
      "confidence_tier": "High",
      "source": "BERT+GPT"
    },
    {
      "knowledge": "programming language",
      "confidence_score": 0.831,
      "confidence_tier": "High",
      "source": "BERT+GPT"
    },
    {
      "knowledge": "data analysis tools",
      "confidence_score": 0.83,
      "confidence_tier": "High",
      "source": "BERT+GPT"
    },
    {
      "knowledge": "Python",
      "confidence_score": 0.75,
      "confidence_tier": "Medium High",
      "source": "GPT"
    },
    {
      "knowledge": "MSc",
      "confidence_score": 0.532,
      "confidence_tier": "Medium Low",
      "source": "BERT (standalone)"
    },
    {
      "knowledge": "a",
      "confidence_score": 0.532,
      "confidence_tier": "Medium Low",
      "source": "BERT (standalone)"
    },
    {
      "knowledge": "BSc",
      "confidence_score": 0.532,
      "confidence_tier": "Medium Low",
      "source": "BERT (standalone)"
    },
    {
      "knowledge": "MSc",
      "confidence_score": 0.532,
      "confidence_tier": "Medium Low",
      "source": "BERT (standalone)"
    },
    {
      "knowledge": "BSc",
      "confidence_score": 0.532,
      "confidence_tier": "Medium Low",
      "source": "BERT (standalone)"
    }
  ],
  "coverage_analysis": {
    "skill_coverage": {
      "digital_literacy": 0.23838695371676222,
      "data_analysis": 0.30532298503347544,
      "ai_literacy_ethics": 0.368471086420112
    },
    "knowledge_coverage": {
      "computational_thinking": 0.5030238095194103,
      "digital_literacy": 0.45688922507464885,
      "algorithms_programming": 0.5287391978591681,
      "data_analysis": 0.4257308473348617,
      "basic_job_skills_ohs": 0.43921337617635736,
      "structured_programming": 0.5125084211468698,
      "oop": 0.5999999642372132,
      "multimedia_programming": 0.45815404192507275,
      "mobile_development": 0.41351037315130246,
      "game_programming": 0.42016061887443074
    },
    "combined_coverage": {
      "audio_editing": 0.0,
      "structured_programming": 0.5125084211468698,
      "graphics_multimedia": 0.0,
      "digital_literacy": 0.45688922507464885,
      "oop": 0.5999999642372132,
      "workforce_insights": 0.0,
      "game_modeling": 0.0,
      "ai_literacy_ethics": 0.368471086420112,
      "game_programming": 0.42016061887443074,
      "computational_thinking": 0.5030238095194103,
      "multimedia_programming": 0.45815404192507275,
      "basic_job_skills_ohs": 0.43921337617635736,
      "ai_development": 0.0,
      "mobile_development": 0.41351037315130246,
      "web_development": 0.0,
      "network_technology": 0.0,
      "algorithms_programming": 0.5287391978591681,
      "data_analysis": 0.4257308473348617,
      "database_systems": 0.0
    },
    "metrics": {
      "total_components": 19,
      "covered_components": 11,
      "coverage_percentage": 0.2698105769326025,
      "skill_coverage_pct": 0.048009527640544725,
      "knowledge_coverage_pct": 0.25041736185785973,
      "avg_skill_confidence": 0.6217656791070624,
      "avg_knowledge_confidence": 0.7083186633678582,
      "hard_skill_count": 6,
      "soft_skill_count": 2,
      "knowledge_count": 13
    },
    "missing_components": [
      "audio_editing",
      "graphics_multimedia",
      "workforce_insights",
      "game_modeling",
      "ai_development",
      "web_development",
      "network_technology",
      "database_systems"
    ],
    "coverage_gaps": [
      {
        "component": "audio_editing",
        "coverage_weight": 0.0,
        "severity": "high",
        "suggestion": "Consider adding more specific skills in this area"
      },
      {
        "component": "structured_programming",
        "coverage_weight": 0.513,
        "severity": "low",
        "suggestion": "Add both theoretical and practical aspects"
      },
      {
        "component": "graphics_multimedia",
        "coverage_weight": 0.0,
        "severity": "high",
        "suggestion": "Consider adding more specific skills in this area"
      },
      {
        "component": "digital_literacy",
        "coverage_weight": 0.457,
        "severity": "medium",
        "suggestion": "Include more technical knowledge items"
      },
      {
        "component": "oop",
        "coverage_weight": 0.6,
        "severity": "low",
        "suggestion": "Add both theoretical and practical aspects"
      },
      {
        "component": "workforce_insights",
        "coverage_weight": 0.0,
        "severity": "high",
        "suggestion": "Consider adding more specific skills in this area"
      },
      {
        "component": "game_modeling",
        "coverage_weight": 0.0,
        "severity": "high",
        "suggestion": "Consider adding more specific skills in this area"
      },
      {
        "component": "ai_literacy_ethics",
        "coverage_weight": 0.368,
        "severity": "medium",
        "suggestion": "Include more technical knowledge items"
      },
      {
        "component": "game_programming",
        "coverage_weight": 0.42,
        "severity": "medium",
        "suggestion": "Include more technical knowledge items"
      },
      {
        "component": "computational_thinking",
        "coverage_weight": 0.503,
        "severity": "low",
        "suggestion": "Add both theoretical and practical aspects"
      },
      {
        "component": "multimedia_programming",
        "coverage_weight": 0.458,
        "severity": "medium",
        "suggestion": "Include more technical knowledge items"
      },
      {
        "component": "basic_job_skills_ohs",
        "coverage_weight": 0.439,
        "severity": "medium",
        "suggestion": "Include more technical knowledge items"
      },
      {
        "component": "ai_development",
        "coverage_weight": 0.0,
        "severity": "high",
        "suggestion": "Consider adding more specific skills in this area"
      },
      {
        "component": "mobile_development",
        "coverage_weight": 0.414,
        "severity": "medium",
        "suggestion": "Include more technical knowledge items"
      },
      {
        "component": "web_development",
        "coverage_weight": 0.0,
        "severity": "high",
        "suggestion": "Consider adding more specific skills in this area"
      },
      {
        "component": "network_technology",
        "coverage_weight": 0.0,
        "severity": "high",
        "suggestion": "Consider adding more specific skills in this area"
      },
      {
        "component": "algorithms_programming",
        "coverage_weight": 0.529,
        "severity": "low",
        "suggestion": "Add both theoretical and practical aspects"
      },
      {
        "component": "data_analysis",
        "coverage_weight": 0.426,
        "severity": "medium",
        "suggestion": "Include more technical knowledge items"
      },
      {
        "component": "database_systems",
        "coverage_weight": 0.0,
        "severity": "high",
        "suggestion": "Consider adding more specific skills in this area"
      }
    ]
  },
  "extraction_metrics": {
    "bert_skill_count": 3,
    "gpt_skill_count": 6,
    "fused_skill_count": 8,
    "model_agreement": 0.0,
    "match_count": 0,
    "extraction_time": 4.715246677398682
  }
}