{
  "job_id": "in-38f7e8fab650ef93",
  "text": "Salesforce Maps ### What your day could look like Analysing requirements and collaborating on the design of functional and/or technical Salesforce solutions. Implement functional and/or technical Salesforce solutions using appropriate programmatic and configuration -based Salesforce tools. Unit, integration, and user acceptance testing of solutions to meet requirements and edge cases. Ensuring smooth deployment and releases into production systems. Identify areas for system maintenance and improvement. Supporting BAU use of the live Salesforce implementation (support queries, training, and user feedback). Our Office First Approach There\u2019s a reason you visit your friends in person, live with your family and don\u2019t do dinners over Zoom.",
  "skills": [
    {
      "skill": "analyze requirements",
      "type": "Hard",
      "bloom": "Analyze",
      "confidence_score": 1.0,
      "confidence_tier": "Very High",
      "source": "BERT+GPT",
      "semantic_density": 0.89,
      "context_agreement": 1.22
    },
    {
      "skill": "collaborate on design of Salesforce solutions",
      "type": "Hard",
      "bloom": "Create",
      "confidence_score": 0.718,
      "confidence_tier": "Medium High",
      "source": "GPT",
      "semantic_density": 0.8,
      "context_agreement": 0.95
    },
    {
      "skill": "implement Salesforce solutions",
      "type": "Hard",
      "bloom": "Apply",
      "confidence_score": 0.73,
      "confidence_tier": "Medium High",
      "source": "GPT",
      "semantic_density": 0.88,
      "context_agreement": 0.95
    },
    {
      "skill": "conduct unit testing",
      "type": "Hard",
      "bloom": "Evaluate",
      "confidence_score": 0.695,
      "confidence_tier": "Medium",
      "source": "GPT",
      "semantic_density": 0.78,
      "context_agreement": 0.95
    },
    {
      "skill": "conduct integration testing",
      "type": "Hard",
      "bloom": "Evaluate",
      "confidence_score": 0.706,
      "confidence_tier": "Medium High",
      "source": "GPT",
      "semantic_density": 0.85,
      "context_agreement": 0.95
    },
    {
      "skill": "conduct user acceptance testing",
      "type": "Hard",
      "bloom": "Evaluate",
      "confidence_score": 0.997,
      "confidence_tier": "Very High",
      "source": "BERT+GPT",
      "semantic_density": 0.8,
      "context_agreement": 1.2
    },
    {
      "skill": "ensure smooth deployment",
      "type": "Hard",
      "bloom": "Apply",
      "confidence_score": 1.0,
      "confidence_tier": "Very High",
      "source": "BERT+GPT",
      "semantic_density": 1.0,
      "context_agreement": 1.23
    },
    {
      "skill": "identify areas for system maintenance",
      "type": "Hard",
      "bloom": "Analyze",
      "confidence_score": 1.0,
      "confidence_tier": "Very High",
      "source": "BERT+GPT",
      "semantic_density": 0.8,
      "context_agreement": 1.24
    },
    {
      "skill": "support BAU use of Salesforce",
      "type": "Hard",
      "bloom": "Apply",
      "confidence_score": 0.522,
      "confidence_tier": "Medium Low",
      "source": "GPT",
      "semantic_density": 0.75,
      "context_agreement": 0.95
    },
    {
      "skill": "collaborating on the design of functional",
      "type": "Hard",
      "bloom": "Create",
      "confidence_score": 0.636,
      "confidence_tier": "Medium",
      "source": "BERT (standalone)",
      "semantic_density": 0.78,
      "context_agreement": 0.86
    },
    {
      "skill": "/ or technical Salesforce solutions.",
      "type": "Hard",
      "bloom": "Apply",
      "confidence_score": 0.485,
      "confidence_tier": "Low",
      "source": "BERT (standalone)",
      "semantic_density": 0.79,
      "context_agreement": 0.86
    },
    {
      "skill": "Implement functional",
      "type": "Hard",
      "bloom": "Apply",
      "confidence_score": 0.65,
      "confidence_tier": "Medium",
      "source": "BERT (standalone)",
      "semantic_density": 0.89,
      "context_agreement": 0.86
    },
    {
      "skill": "/ or technical Salesforce solutions",
      "type": "Hard",
      "bloom": "Apply",
      "confidence_score": 0.484,
      "confidence_tier": "Low",
      "source": "BERT (standalone)",
      "semantic_density": 0.79,
      "context_agreement": 0.86
    },
    {
      "skill": "Unit",
      "type": "Hard",
      "bloom": "Apply",
      "confidence_score": 0.478,
      "confidence_tier": "Low",
      "source": "BERT (standalone)",
      "semantic_density": 0.72,
      "context_agreement": 0.86
    },
    {
      "skill": "integration",
      "type": "Hard",
      "bloom": "Apply",
      "confidence_score": 0.496,
      "confidence_tier": "Low",
      "source": "BERT (standalone)",
      "semantic_density": 0.9,
      "context_agreement": 0.86
    },
    {
      "skill": "meet requirements",
      "type": "Hard",
      "bloom": "Apply",
      "confidence_score": 0.49,
      "confidence_tier": "Low",
      "source": "BERT (standalone)",
      "semantic_density": 0.84,
      "context_agreement": 0.86
    },
    {
      "skill": "edge cases.",
      "type": "Hard",
      "bloom": "Apply",
      "confidence_score": 0.481,
      "confidence_tier": "Low",
      "source": "BERT (standalone)",
      "semantic_density": 0.75,
      "context_agreement": 0.86
    },
    {
      "skill": "releases into production systems.",
      "type": "Hard",
      "bloom": "Apply",
      "confidence_score": 0.488,
      "confidence_tier": "Low",
      "source": "BERT (standalone)",
      "semantic_density": 0.83,
      "context_agreement": 0.86
    },
    {
      "skill": "improvement.",
      "type": "Hard",
      "bloom": "Create",
      "confidence_score": 0.534,
      "confidence_tier": "Medium Low",
      "source": "BERT (standalone)",
      "semantic_density": 0.9,
      "context_agreement": 0.86
    },
    {
      "skill": "Supporting BAU",
      "type": "Hard",
      "bloom": "Evaluate",
      "confidence_score": 0.523,
      "confidence_tier": "Medium Low",
      "source": "BERT (standalone)",
      "semantic_density": 0.8,
      "context_agreement": 0.86
    }
  ],
  "knowledge": [
    {
      "knowledge": "Salesforce",
      "confidence_score": 0.831,
      "confidence_tier": "High",
      "source": "BERT+GPT"
    },
    {
      "knowledge": "Salesforce Maps",
      "confidence_score": 0.75,
      "confidence_tier": "Medium High",
      "source": "GPT"
    },
    {
      "knowledge": "programmatic tools",
      "confidence_score": 0.75,
      "confidence_tier": "Medium High",
      "source": "GPT"
    },
    {
      "knowledge": "configuration-based tools",
      "confidence_score": 0.75,
      "confidence_tier": "Medium High",
      "source": "GPT"
    },
    {
      "knowledge": "integration testing",
      "confidence_score": 0.75,
      "confidence_tier": "Medium High",
      "source": "GPT"
    },
    {
      "knowledge": "user acceptance testing",
      "confidence_score": 0.75,
      "confidence_tier": "Medium High",
      "source": "GPT"
    },
    {
      "knowledge": "production systems",
      "confidence_score": 0.75,
      "confidence_tier": "Medium High",
      "source": "GPT"
    },
    {
      "knowledge": "system maintenance",
      "confidence_score": 0.75,
      "confidence_tier": "Medium High",
      "source": "GPT"
    },
    {
      "knowledge": "integration,",
      "confidence_score": 0.532,
      "confidence_tier": "Medium Low",
      "source": "BERT (standalone)"
    },
    {
      "knowledge": "live",
      "confidence_score": 0.532,
      "confidence_tier": "Medium Low",
      "source": "BERT (standalone)"
    },
    {
      "knowledge": "training,",
      "confidence_score": 0.532,
      "confidence_tier": "Medium Low",
      "source": "BERT (standalone)"
    },
    {
      "knowledge": "user feedback).",
      "confidence_score": 0.532,
      "confidence_tier": "Medium Low",
      "source": "BERT (standalone)"
    }
  ],
  "coverage_analysis": {
    "skill_coverage": {
      "computational_thinking": 0.35177700275444285,
      "digital_literacy": 0.2684927743206614,
      "algorithms_programming": 0.36676006268562766,
      "ai_development": 0.4771196084776526,
      "workforce_insights": 0.5900430712216629,
      "basic_job_skills_ohs": 0.5039949173430411,
      "structured_programming": 0.3273804372305656
    },
    "knowledge_coverage": {
      "computational_thinking": 0.3337062120437623,
      "digital_literacy": 0.3307914018630982,
      "algorithms_programming": 0.3360854029655457,
      "workforce_insights": 0.3327710151672364,
      "basic_job_skills_ohs": 0.3521610617637635,
      "structured_programming": 0.3722790956497193,
      "oop": 0.33175377845764165,
      "multimedia_programming": 0.3626816868782044,
      "game_programming": 0.38190543651580816
    },
    "combined_coverage": {
      "audio_editing": 0.0,
      "structured_programming": 0.3722790956497193,
      "graphics_multimedia": 0.0,
      "digital_literacy": 0.3307914018630982,
      "oop": 0.33175377845764165,
      "workforce_insights": 0.5900430712216629,
      "game_modeling": 0.0,
      "ai_literacy_ethics": 0.0,
      "game_programming": 0.38190543651580816,
      "computational_thinking": 0.35177700275444285,
      "multimedia_programming": 0.3626816868782044,
      "basic_job_skills_ohs": 0.5039949173430411,
      "ai_development": 0.4771196084776526,
      "mobile_development": 0.0,
      "web_development": 0.0,
      "network_technology": 0.0,
      "algorithms_programming": 0.36676006268562766,
      "data_analysis": 0.0,
      "database_systems": 0.0
    },
    "metrics": {
      "total_components": 19,
      "covered_components": 10,
      "coverage_percentage": 0.21416347693931045,
      "skill_coverage_pct": 0.15187199337019233,
      "knowledge_coverage_pct": 0.16495447848972522,
      "avg_skill_confidence": 0.6555857741031074,
      "avg_knowledge_confidence": 0.6840416666666668,
      "hard_skill_count": 20,
      "soft_skill_count": 0,
      "knowledge_count": 12
    },
    "missing_components": [
      "audio_editing",
      "graphics_multimedia",
      "game_modeling",
      "ai_literacy_ethics",
      "mobile_development",
      "web_development",
      "network_technology",
      "data_analysis",
      "database_systems"
    ],
    "coverage_gaps": [
      {
        "component": "audio_editing",
        "coverage_weight": 0.0,
        "severity": "high",
        "suggestion": "Consider adding more specific skills in this area"
      },
      {
        "component": "structured_programming",
        "coverage_weight": 0.372,
        "severity": "medium",
        "suggestion": "Include more technical knowledge items"
      },
      {
        "component": "graphics_multimedia",
        "coverage_weight": 0.0,
        "severity": "high",
        "suggestion": "Consider adding more specific skills in this area"
      },
      {
        "component": "digital_literacy",
        "coverage_weight": 0.331,
        "severity": "medium",
        "suggestion": "Include more technical knowledge items"
      },
      {
        "component": "oop",
        "coverage_weight": 0.332,
        "severity": "medium",
        "suggestion": "Include more technical knowledge items"
      },
      {
        "component": "workforce_insights",
        "coverage_weight": 0.59,
        "severity": "low",
        "suggestion": "Add both theoretical and practical aspects"
      },
      {
        "component": "game_modeling",
        "coverage_weight": 0.0,
        "severity": "high",
        "suggestion": "Consider adding more specific skills in this area"
      },
      {
        "component": "ai_literacy_ethics",
        "coverage_weight": 0.0,
        "severity": "high",
        "suggestion": "Consider adding more specific skills in this area"
      },
      {
        "component": "game_programming",
        "coverage_weight": 0.382,
        "severity": "medium",
        "suggestion": "Include more technical knowledge items"
      },
      {
        "component": "computational_thinking",
        "coverage_weight": 0.352,
        "severity": "medium",
        "suggestion": "Include more technical knowledge items"
      },
      {
        "component": "multimedia_programming",
        "coverage_weight": 0.363,
        "severity": "medium",
        "suggestion": "Include more technical knowledge items"
      },
      {
        "component": "basic_job_skills_ohs",
        "coverage_weight": 0.504,
        "severity": "low",
        "suggestion": "Add both theoretical and practical aspects"
      },
      {
        "component": "ai_development",
        "coverage_weight": 0.477,
        "severity": "medium",
        "suggestion": "Include more technical knowledge items"
      },
      {
        "component": "mobile_development",
        "coverage_weight": 0.0,
        "severity": "high",
        "suggestion": "Consider adding more specific skills in this area"
      },
      {
        "component": "web_development",
        "coverage_weight": 0.0,
        "severity": "high",
        "suggestion": "Consider adding more specific skills in this area"
      },
      {
        "component": "network_technology",
        "coverage_weight": 0.0,
        "severity": "high",
        "suggestion": "Consider adding more specific skills in this area"
      },
      {
        "component": "algorithms_programming",
        "coverage_weight": 0.367,
        "severity": "medium",
        "suggestion": "Include more technical knowledge items"
      },
      {
        "component": "data_analysis",
        "coverage_weight": 0.0,
        "severity": "high",
        "suggestion": "Consider adding more specific skills in this area"
      },
      {
        "component": "database_systems",
        "coverage_weight": 0.0,
        "severity": "high",
        "suggestion": "Consider adding more specific skills in this area"
      }
    ]
  },
  "extraction_metrics": {
    "bert_skill_count": 15,
    "gpt_skill_count": 9,
    "fused_skill_count": 20,
    "model_agreement": 0.2527427633603414,
    "match_count": 4,
    "extraction_time": 7.050818204879761
  }
}